<?xml version='1.0' encoding='utf-8'?>
<estacio><dataGravacioFitxer>18/11/2025 12:30:58</dataGravacioFitxer><codi>TV3000280</codi><nom>Castellgali - TV3</nom><idFont>5</idFont><dataLocalCaptura>18/11/2025 12:30:00</dataLocalCaptura><dataUTCRecollida>18/11/2025 11:30:00</dataUTCRecollida><tempCelsius>12.0</tempCelsius><tempMaxCelsius>20.7</tempMaxCelsius><tempMinCelsius>8.1</tempMinCelsius><humitat>67</humitat><velocitatVent>2.3</velocitatVent><dirVentGraus>84</dirVentGraus><dirVentRoseta>---</dirVentRoseta><ratxaMaximaVent>---</ratxaMaximaVent><precipitacioAc24h>0</precipitacioAc24h><pressio>1013</pressio></estacio>