<?xml version='1.0' encoding='utf-8'?>
<estacio><dataGravacioFitxer>21/04/2026 13:31:11</dataGravacioFitxer><codi>TV3000280</codi><nom>Castellgali - TV3</nom><idFont>5</idFont><dataLocalCaptura>21/04/2026 13:31:00</dataLocalCaptura><dataUTCRecollida>21/04/2026 11:30:32</dataUTCRecollida><tempCelsius>25.9</tempCelsius><tempMaxCelsius>25.9</tempMaxCelsius><tempMinCelsius>4.3</tempMinCelsius><humitat>29</humitat><velocitatVent>2.2</velocitatVent><dirVentGraus>161</dirVentGraus><dirVentRoseta>---</dirVentRoseta><ratxaMaximaVent>---</ratxaMaximaVent><precipitacioAc24h>0</precipitacioAc24h><pressio>1013</pressio></estacio>